./.gitignore
./.python-version
./PKG-INFO
./README.md
./main.py
./pyproject.toml
./requirements-dev.lock
./requirements.lock
./.github/workflows/publish.yml
./.github/workflows/test.yml
./lib/__init__.py
./lib/dbt.py
./lib/utils.py
./tests/test_cli.py
./tests/jaffle_shop_duckdb/.devcontainer.json
./tests/jaffle_shop_duckdb/.gitignore
./tests/jaffle_shop_duckdb/.sqlfluff
./tests/jaffle_shop_duckdb/.sqlfluffignore
./tests/jaffle_shop_duckdb/Dockerfile
./tests/jaffle_shop_duckdb/LICENSE
./tests/jaffle_shop_duckdb/README.md
./tests/jaffle_shop_duckdb/RELEASE.md
./tests/jaffle_shop_duckdb/dbt-completion.bash
./tests/jaffle_shop_duckdb/dbt_project.yml
./tests/jaffle_shop_duckdb/profiles.yml
./tests/jaffle_shop_duckdb/requirements-dev.txt
./tests/jaffle_shop_duckdb/requirements.in
./tests/jaffle_shop_duckdb/requirements.txt
./tests/jaffle_shop_duckdb/.github/workflows/validate_on_platforms.yml
./tests/jaffle_shop_duckdb/.vscode/extensions.json
./tests/jaffle_shop_duckdb/.vscode/tasks.json
./tests/jaffle_shop_duckdb/etc/dbdiagram_definition.txt
./tests/jaffle_shop_duckdb/etc/jaffle_shop_erd.png
./tests/jaffle_shop_duckdb/images/dbt_full_deploy_commands.png
./tests/jaffle_shop_duckdb/images/dbt_performance.png
./tests/jaffle_shop_duckdb/images/open_in_codespaces.png
./tests/jaffle_shop_duckdb/models/customers.sql
./tests/jaffle_shop_duckdb/models/docs.md
./tests/jaffle_shop_duckdb/models/orders.sql
./tests/jaffle_shop_duckdb/models/overview.md
./tests/jaffle_shop_duckdb/models/schema.yml
./tests/jaffle_shop_duckdb/models/staging/schema.yml
./tests/jaffle_shop_duckdb/models/staging/stg_customers.sql
./tests/jaffle_shop_duckdb/models/staging/stg_orders.sql
./tests/jaffle_shop_duckdb/models/staging/stg_payments.sql
./tests/jaffle_shop_duckdb/seeds/.gitkeep
./tests/jaffle_shop_duckdb/seeds/raw_customers.csv
./tests/jaffle_shop_duckdb/seeds/raw_orders.csv
./tests/jaffle_shop_duckdb/seeds/raw_payments.csv
dbtx-0.1.0.dist-info/METADATA
dbtx-0.1.0.dist-info/WHEEL
dbtx-0.1.0.dist-info/entry_points.txt
dbtx-0.1.0.dist-info/RECORD
