Metadata-Version: 2.3
Name: dbtx
Version: 0.1.0
Summary: Add your description here
Requires-Python: >=3.11
Requires-Dist: pyyaml>=6.0.2
Requires-Dist: uv>=0.4.7
